gribscan/__init__.py
gribscan/_version.py
gribscan/gribscan.py
gribscan/gridutils.py
gribscan/magician.py
gribscan/rawgribcodec.py
gribscan/tools.py
gribscan-0.0.15.dist-info/licenses/LICENSE
gribscan-0.0.15.dist-info/METADATA
gribscan-0.0.15.dist-info/WHEEL
gribscan-0.0.15.dist-info/entry_points.txt
gribscan-0.0.15.dist-info/top_level.txt
gribscan-0.0.15.dist-info/RECORD
