Metadata-Version: 2.4
Name: gribscan
Version: 0.0.15
Summary: Create indices for GRIB files and provide an xarray interface.
Author: Tobias Kölling, Lukas Kluft, Thomas Rackow
License: MIT License
Keywords: fsspec,grib,zarr
Classifier: Programming Language :: Python :: 3
License-File: LICENSE
Requires-Dist: cfgrib>=0.9.9.0
Requires-Dist: click
Requires-Dist: eccodes
Requires-Dist: numcodecs>=0.10.0
Requires-Dist: numpy
Requires-Dist: scipy
Requires-Dist: xarray>=2025.9.0
Provides-Extra: docs
Requires-Dist: sphinx; extra == "docs"
Requires-Dist: myst-parser; extra == "docs"
Requires-Dist: sphinx-diagrams; extra == "docs"
Requires-Dist: sphinx-book-theme; extra == "docs"
Dynamic: license-file
